build/lib/build/lib/build/lib/build/lib/ztfin2p3/__init__.py
build/lib/build/lib/build/lib/build/lib/ztfin2p3/aperture.py
build/lib/build/lib/build/lib/build/lib/ztfin2p3/builder.py
build/lib/build/lib/build/lib/build/lib/ztfin2p3/catalog.py
build/lib/build/lib/build/lib/build/lib/ztfin2p3/io.py
build/lib/build/lib/build/lib/build/lib/ztfin2p3/metadata.py
build/lib/build/lib/build/lib/build/lib/ztfin2p3/science.py
build/lib/build/lib/build/lib/build/lib/ztfin2p3/startable.py
build/lib/build/lib/build/lib/build/lib/ztfin2p3/ubercal.py
build/lib/build/lib/build/lib/build/lib/ztfin2p3/calibration/__init__.py
build/lib/build/lib/build/lib/build/lib/ztfin2p3/calibration/bias.py
build/lib/build/lib/build/lib/build/lib/ztfin2p3/calibration/builder.py
build/lib/build/lib/build/lib/build/lib/ztfin2p3/calibration/flat.py
build/lib/build/lib/build/lib/build/lib/ztfin2p3/calibration/starflat.py
build/lib/build/lib/build/lib/build/lib/ztfin2p3/config/__init__.py
build/lib/build/lib/build/lib/build/lib/ztfin2p3/pipe/__init__.py
build/lib/build/lib/build/lib/build/lib/ztfin2p3/pipe/basepipe.py
build/lib/build/lib/build/lib/build/lib/ztfin2p3/pipe/calibrationpipe.py
build/lib/build/lib/build/lib/build/lib/ztfin2p3/pipe/flatpipe.py
build/lib/build/lib/build/lib/build/lib/ztfin2p3/simulations/__init__.py
build/lib/build/lib/build/lib/build/lib/ztfin2p3/simulations/effects.py
build/lib/build/lib/build/lib/build/lib/ztfin2p3/simulations/linearmodel.py
build/lib/build/lib/build/lib/build/lib/ztfin2p3/utils/__init__.py
build/lib/build/lib/build/lib/build/lib/ztfin2p3/utils/sparsesolver.py
build/lib/build/lib/build/lib/build/lib/ztfin2p3/utils/tools.py
build/lib/build/lib/build/lib/ztfin2p3/__init__.py
build/lib/build/lib/build/lib/ztfin2p3/aperture.py
build/lib/build/lib/build/lib/ztfin2p3/builder.py
build/lib/build/lib/build/lib/ztfin2p3/catalog.py
build/lib/build/lib/build/lib/ztfin2p3/io.py
build/lib/build/lib/build/lib/ztfin2p3/metadata.py
ztfin2p3-0.4.1.dist-info/LICENSE
ztfin2p3-0.4.1.dist-info/METADATA
ztfin2p3-0.4.1.dist-info/WHEEL
ztfin2p3-0.4.1.dist-info/entry_points.txt
ztfin2p3-0.4.1.dist-info/top_level.txt
ztfin2p3-0.4.1.dist-info/RECORD
